tensorflow_serving_client/__init__.py
tensorflow_serving_client/client.py
tensorflow_serving_client/proto_util.py
tensorflow_serving_client/protos/__init__.py
tensorflow_serving_client/protos/model_pb2.py
tensorflow_serving_client/protos/model_pb2_grpc.py
tensorflow_serving_client/protos/predict_pb2.py
tensorflow_serving_client/protos/predict_pb2_grpc.py
tensorflow_serving_client/protos/prediction_service_pb2.py
tensorflow_serving_client/protos/prediction_service_pb2_grpc.py
tensorflow_serving_client/protos/resource_handle_pb2.py
tensorflow_serving_client/protos/resource_handle_pb2_grpc.py
tensorflow_serving_client/protos/tensor_pb2.py
tensorflow_serving_client/protos/tensor_pb2_grpc.py
tensorflow_serving_client/protos/tensor_shape_pb2.py
tensorflow_serving_client/protos/tensor_shape_pb2_grpc.py
tensorflow_serving_client/protos/types_pb2.py
tensorflow_serving_client/protos/types_pb2_grpc.py
tensorflow_serving_client-1.0.0.data/scripts/tensorflow_serving_client
tensorflow_serving_client-1.0.0.dist-info/LICENSE
tensorflow_serving_client-1.0.0.dist-info/METADATA
tensorflow_serving_client-1.0.0.dist-info/WHEEL
tensorflow_serving_client-1.0.0.dist-info/top_level.txt
tensorflow_serving_client-1.0.0.dist-info/RECORD
